msdb/__init__.py
msdb/db_config.json
msdb/msdb.py
msdb-0.0.8.dist-info/licenses/LICENSE
msdb-0.0.8.dist-info/METADATA
msdb-0.0.8.dist-info/WHEEL
msdb-0.0.8.dist-info/top_level.txt
msdb-0.0.8.dist-info/RECORD
