Metadata-Version: 2.4
Name: msdb
Version: 0.0.8
Summary: Package to manage the metadata associated with the analyses on materials
Author: Gauthier Patin
Author-email: Gauthier Patin <g.patin@monemail.com>
License:                     GNU GENERAL PUBLIC LICENSE
Project-URL: Homepage, https://github.com/g-patin/msdb
Keywords: material science,analyses,databases,metadata
Classifier: Programming Language :: Python :: 3
Classifier: License :: OSI Approved :: GNU General Public License v3 (GPLv3)
Classifier: Operating System :: OS Independent
Requires-Python: >=3.8
License-File: LICENSE
Requires-Dist: openpyxl
Requires-Dist: jupyterlab
Requires-Dist: ipywidgets
Dynamic: license-file
